README.md
setup.cfg
setup.py
aiokts/__init__.py
aiokts/daemon.py
aiokts/manage.py
aiokts/managecommands.py
aiokts/settings.py
aiokts.egg-info/PKG-INFO
aiokts.egg-info/SOURCES.txt
aiokts.egg-info/dependency_links.txt
aiokts.egg-info/requires.txt
aiokts.egg-info/top_level.txt
aiokts/store/__init__.py
aiokts/store/store.py
aiokts/store/base_accessors/__init__.py
aiokts/store/base_accessors/base_mongodb.py
aiokts/store/base_accessors/base_mysql.py
aiokts/store/base_accessors/base_pg.py
aiokts/store/base_accessors/base_tarantool.py
aiokts/store/base_accessors/mysql_utils/__init__.py
aiokts/store/models/__init__.py
aiokts/util/__init__.py
aiokts/util/arguments.py
aiokts/util/argumentslib.py
aiokts/util/json_utils.py
aiokts/web/__init__.py
aiokts/web/api_hour.py
aiokts/web/application.py
aiokts/web/arguments_params.py
aiokts/web/context.py
aiokts/web/error.py
aiokts/web/handler.py
aiokts/web/request.py
aiokts/web/response.py
aiokts/web/server.py
aiokts/web/view.py