Metadata-Version: 1.1
Name: aiokts
Version: 0.2.18
Summary: Tuned asyncio and aiohttp classes for simpler creation of powerful APIs
Home-page: https://github.com/KTSStudio/aiokts
Author: KTS
Author-email: aiokts@ktsstudio.ru
License: MIT
Download-URL: https://github.com/KTSStudio/aiokts/tarball/v0.2.18
Keywords: aiohttp asyncio python 3.5 api
Platform: UNKNOWN
Classifier: Development Status :: 3 - Alpha
Classifier: Intended Audience :: Developers
Classifier: Topic :: Software Development :: Build Tools
Classifier: License :: OSI Approved :: MIT License
Classifier: Programming Language :: Python :: 3.5
